odoo8_addon_web_advanced_search_wildcard-8.0.1.0.0.99.dev13-py2.7-nspkg.pth
odoo8_addon_web_advanced_search_wildcard-8.0.1.0.0.99.dev13.dist-info/METADATA
odoo8_addon_web_advanced_search_wildcard-8.0.1.0.0.99.dev13.dist-info/RECORD
odoo8_addon_web_advanced_search_wildcard-8.0.1.0.0.99.dev13.dist-info/WHEEL
odoo8_addon_web_advanced_search_wildcard-8.0.1.0.0.99.dev13.dist-info/namespace_packages.txt
odoo8_addon_web_advanced_search_wildcard-8.0.1.0.0.99.dev13.dist-info/top_level.txt
odoo_addons/web_advanced_search_wildcard/README.rst
odoo_addons/web_advanced_search_wildcard/__init__.py
odoo_addons/web_advanced_search_wildcard/__openerp__.py
odoo_addons/web_advanced_search_wildcard/i18n/de.po
odoo_addons/web_advanced_search_wildcard/i18n/es.po
odoo_addons/web_advanced_search_wildcard/i18n/fi.po
odoo_addons/web_advanced_search_wildcard/i18n/fr.po
odoo_addons/web_advanced_search_wildcard/i18n/pt_BR.po
odoo_addons/web_advanced_search_wildcard/i18n/sl.po
odoo_addons/web_advanced_search_wildcard/i18n/tr.po
odoo_addons/web_advanced_search_wildcard/i18n/web_advanced_search_wildcard.pot
odoo_addons/web_advanced_search_wildcard/static/description/icon.png
odoo_addons/web_advanced_search_wildcard/static/description/screenshot.png
odoo_addons/web_advanced_search_wildcard/static/src/js/search.js
odoo_addons/web_advanced_search_wildcard/views/template.xml
